spotii_billing_client/__init__.py
spotii_billing_client/api_client.py
spotii_billing_client/configuration.py
spotii_billing_client/rest.py
spotii_billing_client/api/__init__.py
spotii_billing_client/api/accounts_api.py
spotii_billing_client/api/billing_addresses_api.py
spotii_billing_client/api/configurations_api.py
spotii_billing_client/api/installment_estimate_api.py
spotii_billing_client/api/installments_api.py
spotii_billing_client/api/invoices_api.py
spotii_billing_client/api/payment_methods_api.py
spotii_billing_client/api/payments_api.py
spotii_billing_client/api/plugin_configurations_api.py
spotii_billing_client/api/push_notifications_api.py
spotii_billing_client/api/tenants_api.py
spotii_billing_client/api/transactions_api.py
spotii_billing_client/models/__init__.py
spotii_billing_client/models/account.py
spotii_billing_client/models/billing_address.py
spotii_billing_client/models/calculated_payments_serilizer.py
spotii_billing_client/models/card_details.py
spotii_billing_client/models/configuration.py
spotii_billing_client/models/configuration_update.py
spotii_billing_client/models/esstimation_payment_serilizer.py
spotii_billing_client/models/estimation.py
spotii_billing_client/models/installment_serilizer.py
spotii_billing_client/models/installments.py
spotii_billing_client/models/invoice.py
spotii_billing_client/models/invoice_item.py
spotii_billing_client/models/payment.py
spotii_billing_client/models/payment_method.py
spotii_billing_client/models/plugin_configuration.py
spotii_billing_client/models/plugin_configuration_update.py
spotii_billing_client/models/push_notification.py
spotii_billing_client/models/tenant.py
spotii_billing_client/models/transaction.py
test/__init__.py
test/test_account.py
test/test_accounts_api.py
test/test_billing_address.py
test/test_billing_addresses_api.py
test/test_calculated_payments_serilizer.py
test/test_card_details.py
test/test_configuration.py
test/test_configuration_update.py
test/test_configurations_api.py
spotii_billing_client-1.0.2.dist-info/METADATA
spotii_billing_client-1.0.2.dist-info/WHEEL
spotii_billing_client-1.0.2.dist-info/top_level.txt
spotii_billing_client-1.0.2.dist-info/RECORD
