Metadata-Version: 2.1
Name: spotii-billing-client
Version: 1.0.2
Summary: Spotii Billing API
Home-page: UNKNOWN
Author-email: hello@nuclearo.com
License: UNKNOWN
Keywords: Swagger,Spotii Billing API
Platform: UNKNOWN
Requires-Dist: urllib3 (>=1.15)
Requires-Dist: six (>=1.10)
Requires-Dist: certifi
Requires-Dist: python-dateutil
